LICENSE
License
MANIFEST.in
README.rst
setup.py
grupa47.egg-info/PKG-INFO
grupa47.egg-info/SOURCES.txt
grupa47.egg-info/dependency_links.txt
grupa47.egg-info/top_level.txt
resurse/__init__.py
resurse/object_one.py
resurse/object_two.py